Workbook

Sheet README & scoring
A1: Google Ranking Signals — Team Compliance Checklist
A2: Derived exclusively from Google's own public documentation (How Search Works + Google Search Central). Every item cites its source.
A4: The honest expert note (read this first)
A5: Google states plainly: it does not guarantee crawling, indexing, or ranking — even for pages that follow every guideline — and it accepts no payment to rank anyone higher. Rankings come from hundreds of signals weighed against live competition, and the weights shift by query type (e.g. freshness matters more for news than for definitions). So this checklist cannot promise #1. What it does: it converts everything Google publicly says it rewards — and everything it says it punishes — into concrete, auditable team actions. A site at 95%+ compliance here has removed nearly every self-inflicted reason Google has to hold it back. That is the highest-probability position a team can manufacture; the rest is competition and time.
A8: How to use
A9: 1. MASTER CHECKLIST — run per site, quarterly (or before any launch). Owner column tells you who does what: Content = writers/editors, Dev = developers, SEO Lead = strategist, All = everyone.
A10: 2. PRE-PUBLISH GATE — the writer's 18-point gate. No page ships until every applicable item is Pass.
A11: 3. SPAM RED LINES — 17 hard don'ts from Google's spam policies. These need 100%. One violation can sink a site.
A12: 4. Set each row's Status (Pass / Fail / In progress / N-A). Compliance % per pillar is computed automatically below.
A13: 5. Targets: 100% on Spam Red Lines · ≥90% overall · no pillar below 80%. Fix Fail items before chasing new content.
A15: Scoring
A16: Compliance % = Pass ÷ (Total − N/A). 'N/A' is for genuinely inapplicable items only (e.g. hreflang on a single-language site) — never for 'too hard'. The per-pillar table below pulls live from the Master Checklist sheet.
A19: Pillar | B19: Total items | C19: Passed | D19: N/A | E19: Compliance %
A20: 1 · Crawl & discovery | B20: =COUNTIF('Master checklist'!$B$2:$B$81,A20) | C20: =COUNTIFS('Master checklist'!$B$2:$B$81,A20,'Master checklist'!$G$2:$G$81,"Pass") | D20: =COUNTIFS('Master checklist'!$B$2:$B$81,A20,'Master checklist'!$G$2:$G$81,"N/A") | E20: =IF((B20-D20)=0,"—",C20/(B20-D20))
A21: 2 · Indexing & technical setup | B21: =COUNTIF('Master checklist'!$B$2:$B$81,A21) | C21: =COUNTIFS('Master checklist'!$B$2:$B$81,A21,'Master checklist'!$G$2:$G$81,"Pass") | D21: =COUNTIFS('Master checklist'!$B$2:$B$81,A21,'Master checklist'!$G$2:$G$81,"N/A") | E21: =IF((B21-D21)=0,"—",C21/(B21-D21))
A22: 3 · Search intent & relevance | B22: =COUNTIF('Master checklist'!$B$2:$B$81,A22) | C22: =COUNTIFS('Master checklist'!$B$2:$B$81,A22,'Master checklist'!$G$2:$G$81,"Pass") | D22: =COUNTIFS('Master checklist'!$B$2:$B$81,A22,'Master checklist'!$G$2:$G$81,"N/A") | E22: =IF((B22-D22)=0,"—",C22/(B22-D22))
A23: 4 · Content quality & E-E-A-T | B23: =COUNTIF('Master checklist'!$B$2:$B$81,A23) | C23: =COUNTIFS('Master checklist'!$B$2:$B$81,A23,'Master checklist'!$G$2:$G$81,"Pass") | D23: =COUNTIFS('Master checklist'!$B$2:$B$81,A23,'Master checklist'!$G$2:$G$81,"N/A") | E23: =IF((B23-D23)=0,"—",C23/(B23-D23))
A24: 5 · Page experience & usability | B24: =COUNTIF('Master checklist'!$B$2:$B$81,A24) | C24: =COUNTIFS('Master checklist'!$B$2:$B$81,A24,'Master checklist'!$G$2:$G$81,"Pass") | D24: =COUNTIFS('Master checklist'!$B$2:$B$81,A24,'Master checklist'!$G$2:$G$81,"N/A") | E24: =IF((B24-D24)=0,"—",C24/(B24-D24))
A25: 6 · Authority, links & reputation | B25: =COUNTIF('Master checklist'!$B$2:$B$81,A25) | C25: =COUNTIFS('Master checklist'!$B$2:$B$81,A25,'Master checklist'!$G$2:$G$81,"Pass") | D25: =COUNTIFS('Master checklist'!$B$2:$B$81,A25,'Master checklist'!$G$2:$G$81,"N/A") | E25: =IF((B25-D25)=0,"—",C25/(B25-D25))
A26: 7 · Spam-policy & safety compliance | B26: =COUNTIF('Master checklist'!$B$2:$B$81,A26) | C26: =COUNTIFS('Master checklist'!$B$2:$B$81,A26,'Master checklist'!$G$2:$G$81,"Pass") | D26: =COUNTIFS('Master checklist'!$B$2:$B$81,A26,'Master checklist'!$G$2:$G$81,"N/A") | E26: =IF((B26-D26)=0,"—",C26/(B26-D26))
A27: 8 · Localization, SERP features & brand | B27: =COUNTIF('Master checklist'!$B$2:$B$81,A27) | C27: =COUNTIFS('Master checklist'!$B$2:$B$81,A27,'Master checklist'!$G$2:$G$81,"Pass") | D27: =COUNTIFS('Master checklist'!$B$2:$B$81,A27,'Master checklist'!$G$2:$G$81,"N/A") | E27: =IF((B27-D27)=0,"—",C27/(B27-D27))
A28: 9 · Monitoring & iteration | B28: =COUNTIF('Master checklist'!$B$2:$B$81,A28) | C28: =COUNTIFS('Master checklist'!$B$2:$B$81,A28,'Master checklist'!$G$2:$G$81,"Pass") | D28: =COUNTIFS('Master checklist'!$B$2:$B$81,A28,'Master checklist'!$G$2:$G$81,"N/A") | E28: =IF((B28-D28)=0,"—",C28/(B28-D28))
A29: TOTAL
A31: Source documents (every checklist item cites one of these)
A32: • How Search Works — crawling, indexing & serving (the 3 stages) https://developers.google.com/search/docs/fundamentals/how-search-works
A33: • How Search Works — how ranking results are determined (the 5 factors) https://www.google.com/intl/en_us/search/howsearchworks/how-search-works/ranking-results/
A34: • Guide to Google Search ranking systems https://developers.google.com/search/docs/appearance/ranking-systems-guide
A35: • Spam policies for Google web search https://developers.google.com/search/docs/essentials/spam-policies
A36: • Creating helpful, reliable, people-first content (+ E-E-A-T, Who/How/Why) https://developers.google.com/search/docs/fundamentals/creating-helpful-content
A37: • Understanding page experience in Google Search results https://developers.google.com/search/docs/appearance/page-experience

Sheet Master checklist
A1: ID | B1: Pillar | C1: Checklist item | D1: What 'done' looks like | E1: Owner | F1: Google source | G1: Status | H1: Evidence / notes
A2: C1 | B2: 1 · Crawl & discovery | C2: XML sitemap covers every indexable URL and is submitted in Search Console | D2: Sitemap auto-updates on publish/edit; submitted in GSC; returns 200; <50k URLs / 50MB per file | E2: Dev | F2: HSW-CRAWL
A3: C2 | B3: 1 · Crawl & discovery | C3: Every important page is reachable via internal links from hub/category pages — no orphans | D3: Priority pages within 3 clicks of homepage; orphan-page report shows zero money pages | E3: SEO Lead | F3: HSW-CRAWL
A4: C3 | B4: 1 · Crawl & discovery | C4: robots.txt allows Googlebot on all index-worthy pages AND the CSS/JS/images needed to render them | D4: Fetch as Google / URL Inspection shows full render; no Disallow on asset folders | E4: Dev | F4: HSW-CRAWL
A5: C4 | B5: 1 · Crawl & discovery | C5: Main content is accessible without login and without heavy user interaction | D5: Anonymous visit shows full article/tool; paywalled content follows Flexible Sampling rules | E5: Dev | F5: HSW-CRAWL
A6: C5 | B6: 1 · Crawl & discovery | C6: Server is fast and stable — no recurring 5xx errors, timeouts, or DNS failures | D6: GSC crawl stats show <1% server errors; TTFB healthy; uptime monitoring in place | E6: Dev | F6: HSW-CRAWL
A7: C6 | B7: 1 · Crawl & discovery | C7: Critical content is visible in the rendered HTML (post-JavaScript) | D7: URL Inspection 'View tested page' shows headings, body text, links; no content that only appears after clicks | E7: Dev | F7: HSW-CRAWL
A8: C7 | B8: 1 · Crawl & discovery | C8: Crawl budget protected on large sites: parameter/filter/pagination URLs controlled | D8: Faceted URLs canonicalized or blocked; no infinite calendar/search-result crawl traps | E8: SEO Lead | F8: HSW-CRAWL
A9: I1 | B9: 2 · Indexing & technical setup | C9: Noindex / nofollow / x-robots headers exist ONLY where intended | D9: Quarterly audit: money pages return index,follow; staging/dev fully blocked | E9: SEO Lead | F9: HSW-INDEX
A10: I2 | B10: 2 · Indexing & technical setup | C10: Every indexable page has a self-referencing absolute canonical tag | D10: Canonical = final 200 URL; no canonical chains; GSC shows 'user-declared canonical' honored | E10: Dev | F10: HSW-INDEX
A11: I3 | B11: 2 · Indexing & technical setup | C11: Near-duplicate pages consolidated — one strong page per intent, not several thin variants | D11: Duplicate clusters merged with 301s; GSC duplicate-without-canonical warnings resolved | E11: SEO Lead | F11: HSW-INDEX
A12: I4 | B12: 2 · Indexing & technical setup | C12: Unique, descriptive <title> per page; unique meta description written for CTR | D12: Titles keyword-forward, no duplication sitewide; descriptions read like ad copy, not keyword lists | E12: Content | F12: HSW-INDEX · HELPFUL
A13: I5 | B13: 2 · Indexing & technical setup | C13: Language declared correctly (lang attribute); hreflang correct on multi-language/region sites | D13: hreflang self-referencing + reciprocal; x-default set; no return-tag errors in GSC | E13: Dev | F13: HSW-INDEX
... A80: M5 | B80: 9 · Monitoring & iteration | C80: Site changelog maintained (content updates, tech changes) to correlate with traffic shifts | D80: Every deploy/content batch logged with date | E80: All | F80: HSW docs (testing ethos)
B81: Pillar compliance → use the README sheet summary

Sheet Pre-publish gate
A1: PRE-PUBLISH GATE — no page ships until every applicable item is Pass
A2: ID | B2: Gate check | C2: Owner | D2: Status | E2: Notes
A3: G1 | B3: One primary intent + target keyword defined; title/H1 carry it naturally | C3: Content
A4: G2 | B4: Title honest and descriptive (displays fully, ~60 chars); meta description written for CTR | C4: Content
A5: G3 | B5: Content is original — adds something competitors don't (data, test, angle, example) | C5: Content
A6: G4 | B6: Topic covered completely; reader won't need to search again | C6: Content
A7: G5 | B7: First-hand experience shown (screenshots/photos/data/testing evidence) | C7: Content
A8: G6 | B8: Facts verified; claims/data linked to sources | C8: Content
A9: G7 | B9: Byline present linking to a real author page; no fake authorship | C9: Content
A10: G8 | B10: Single H1; descriptive H2/H3 outline; keyword variants natural, never stuffed | C10: Content
A11: G9 | B11: Genuine dates only — no fake 'updated' stamps; freshness claims are real | C11: Content
A12: G10 | B12: Internal links to/from related pages with descriptive anchors | C12: Content
A13: G11 | B13: Images compressed with descriptive filenames + alt text | C13: Content
A14: G12 | B14: Structured data added and valid (where eligible) | C14: Dev
... A20: G18 | B20: 'Would I bookmark/share this?' — editor answers yes | C20: Content
B21: Gate score (formula for Excel): =COUNTIF(D3:D20,"Pass")/COUNTA(D3:D20) of applicable items at Pass

Sheet Spam red lines
A1: SPAM RED LINES — 17 hard don'ts. Target: 100% clean. One violation can sink a site.
A2: ID | B2: Violation (never do this) | C2: What Google does about it | D2: Status
A3: T1 | B3: Cloaking (different content to Googlebot vs users) | C3: Manual action / removal from results
A4: T2 | B4: Doorway pages targeting keyword/city variants | C4: Devalued or removed; site-level distrust
A5: T3 | B5: Keyword stuffing | C5: Ranking demotion; page looks low-quality to classifiers
A6: T4 | B6: Hidden text or links | C6: Manual action
A7: T5 | B7: Sneaky redirects | C7: Manual action
A8: T6 | B8: Scraped content with no added value | C8: Not indexed or demoted; original outranks you
A9: T7 | B9: Scaled content abuse (mass auto/AI pages for rankings) | C9: Algorithmic suppression, now part of core systems
A10: T8 | B10: Expired-domain abuse | C10: Manual action; domain's inherited trust discarded
A11: T9 | B11: Site-reputation abuse (parasite SEO) | C11: Manual action; section ranked on its own (or removed)
A12: T10 | B12: Thin affiliate pages (copied merchant descriptions) | C12: Demotion under thin-affiliation policy
A13: T11 | B13: Unmoderated user-generated spam | C13: Page/site quality signals dragged down
A14: T12 | B14: Hacked site / injected spam or malware | C14: Warnings in results; rankings collapse until cleaned
... A19: T17 | B19: Scraping Google (machine-generated traffic) | C19: IP blocks; ToS violation
